avatar_generator/__init__.py
avatar_generator/data/Inconsolata.otf
avatar_generator-0.4.2.dist-info/METADATA
avatar_generator-0.4.2.dist-info/WHEEL
avatar_generator-0.4.2.dist-info/top_level.txt
avatar_generator-0.4.2.dist-info/RECORD
