Metadata-Version: 2.1
Name: avatar-generator
Version: 0.4.2
Summary: Generates default avatars from a given string (such as username).
Home-page: http://github.com/maethor/avatar-generator
Author: Guillaume Subiron
Author-email: maethor+pip@subiron.org
License: WTFPL
Classifier: Programming Language :: Python :: 3
Classifier: Operating System :: OS Independent
Classifier: Intended Audience :: Developers
Requires-Dist: pillow >=9.2.0
